{"featureCount":3,"formatVersion":1,"histograms":{"meta":[{"arrayParams":{"chunkSize":10000,"length":1,"urlTemplate":"hist-5000-{Chunk}.json"},"basesPerBin":"5000"}],"stats":[{"basesPerBin":"5000","max":3,"mean":3}]},"intervals":{"classes":[{"attributes":["Start","End","Strand","Id","Name","Seq_id","Source","Subfeatures","Target_length","Type"],"isArrayAttr":{"Subfeatures":1}},{"attributes":["Start","End","Strand","Gap","Id","Seq_id","Source","Target","Type"],"isArrayAttr":{}},{"attributes":["Start","End","Strand","Id","Seq_id","Source","Target","Type"],"isArrayAttr":{}},{"attributes":["Start","End","Chunk"],"isArrayAttr":{"Sublist":1}}],"count":3,"lazyClass":3,"maxEnd":2548,"minStart":21,"nclist":[[0,21,935,-1,"NODE_8102_length_2562_cov_19.393840:hit:710:4.5.0.0","genemark-NODE_8102_length_2562_cov_19.393840-abinit-gene-0.1-mRNA-1","NODE_8102_length_2562_cov_19.393840","genemark",[[1,458,935,-1,"M477","NODE_8102_length_2562_cov_19.393840:hsp:1858:4.5.0.0","NODE_8102_length_2562_cov_19.393840","genemark","genemark-NODE_8102_length_2562_cov_19.393840-abinit-gene-0.1-mRNA-1 346 822 +","match_part"],[1,21,366,-1,"M345","NODE_8102_length_2562_cov_19.393840:hsp:1859:4.5.0.0","NODE_8102_length_2562_cov_19.393840","genemark","genemark-NODE_8102_length_2562_cov_19.393840-abinit-gene-0.1-mRNA-1 1 345 +","match_part"]],"2562","match"],[0,992,1420,-1,"NODE_8102_length_2562_cov_19.393840:hit:712:4.5.0.0","genemark-NODE_8102_length_2562_cov_19.393840-abinit-gene-0.2-mRNA-1","NODE_8102_length_2562_cov_19.393840","genemark",[[1,1349,1420,-1,"M71","NODE_8102_length_2562_cov_19.393840:hsp:1862:4.5.0.0","NODE_8102_length_2562_cov_19.393840","genemark","genemark-NODE_8102_length_2562_cov_19.393840-abinit-gene-0.2-mRNA-1 233 303 +","match_part"],[1,992,1224,-1,"M232","NODE_8102_length_2562_cov_19.393840:hsp:1863:4.5.0.0","NODE_8102_length_2562_cov_19.393840","genemark","genemark-NODE_8102_length_2562_cov_19.393840-abinit-gene-0.2-mRNA-1 1 232 +","match_part"]],"2562","match"],[0,1795,2548,-1,"NODE_8102_length_2562_cov_19.393840:hit:713:4.5.0.0","genemark-NODE_8102_length_2562_cov_19.393840-abinit-gene-0.3-mRNA-1","NODE_8102_length_2562_cov_19.393840","genemark",[[1,2286,2548,-1,"M262","NODE_8102_length_2562_cov_19.393840:hsp:1864:4.5.0.0","NODE_8102_length_2562_cov_19.393840","genemark","genemark-NODE_8102_length_2562_cov_19.393840-abinit-gene-0.3-mRNA-1 429 690 +","match_part"],[1,1795,2223,-1,"M428","NODE_8102_length_2562_cov_19.393840:hsp:1865:4.5.0.0","NODE_8102_length_2562_cov_19.393840","genemark","genemark-NODE_8102_length_2562_cov_19.393840-abinit-gene-0.3-mRNA-1 1 428 +","match_part"]],"2562","match"]],"urlTemplate":"lf-{Chunk}.json"}}