{"featureCount":1,"formatVersion":1,"histograms":{"meta":[{"arrayParams":{"chunkSize":10000,"length":1,"urlTemplate":"hist-1000-{Chunk}.json"},"basesPerBin":"1000"}],"stats":[{"basesPerBin":"1000","max":1,"mean":1}]},"intervals":{"classes":[{"attributes":["Start","End","Strand","Id","Name","Seq_id","Source","Subfeatures","Target_length","Type"],"isArrayAttr":{"Subfeatures":1}},{"attributes":["Start","End","Strand","Gap","Id","Seq_id","Source","Target","Type"],"isArrayAttr":{}},{"attributes":["Start","End","Strand","Id","Seq_id","Source","Target","Type"],"isArrayAttr":{}},{"attributes":["Start","End","Chunk"],"isArrayAttr":{"Sublist":1}}],"count":1,"lazyClass":3,"maxEnd":253,"minStart":12,"nclist":[[0,12,253,1,"NODE_38512_length_297_cov_2.105882:hit:406:4.5.0.0","genemark-NODE_38512_length_297_cov_2.105882-abinit-gene-0.0-mRNA-1","NODE_38512_length_297_cov_2.105882","genemark",[[1,12,71,1,"M59","NODE_38512_length_297_cov_2.105882:hsp:465:4.5.0.0","NODE_38512_length_297_cov_2.105882","genemark","genemark-NODE_38512_length_297_cov_2.105882-abinit-gene-0.0-mRNA-1 1 59 +","match_part"],[1,138,253,1,"M115","NODE_38512_length_297_cov_2.105882:hsp:466:4.5.0.0","NODE_38512_length_297_cov_2.105882","genemark","genemark-NODE_38512_length_297_cov_2.105882-abinit-gene-0.0-mRNA-1 60 174 +","match_part"]],"297","match"]],"urlTemplate":"lf-{Chunk}.json"}}