{"featureCount":1,"formatVersion":1,"histograms":{"meta":[{"arrayParams":{"chunkSize":10000,"length":1,"urlTemplate":"hist-2000-{Chunk}.json"},"basesPerBin":"2000"}],"stats":[{"basesPerBin":"2000","max":1,"mean":1}]},"intervals":{"classes":[{"attributes":["Start","End","Strand","Id","Name","Score","Seq_id","Source","Subfeatures","Target_length","Type"],"isArrayAttr":{"Subfeatures":1}},{"attributes":["Start","End","Strand","Gap","Id","Score","Seq_id","Source","Target","Type"],"isArrayAttr":{}},{"attributes":["Start","End","Chunk"],"isArrayAttr":{"Sublist":1}}],"count":1,"lazyClass":2,"maxEnd":424,"minStart":49,"nclist":[[0,49,424,1,"NODE_25764_length_426_cov_1.866221:hit:2114:4.5.0.0","augustus-NODE_25764_length_426_cov_1.866221-abinit-gene-0.1-mRNA-1",0.57,"NODE_25764_length_426_cov_1.866221","augustus",[[1,49,266,1,"M217","NODE_25764_length_426_cov_1.866221:hsp:2913:4.5.0.0",0.57,"NODE_25764_length_426_cov_1.866221","augustus","augustus-NODE_25764_length_426_cov_1.866221-abinit-gene-0.1-mRNA-1 1 217 +","match_part"],[1,344,424,1,"M80","NODE_25764_length_426_cov_1.866221:hsp:2914:4.5.0.0",0.57,"NODE_25764_length_426_cov_1.866221","augustus","augustus-NODE_25764_length_426_cov_1.866221-abinit-gene-0.1-mRNA-1 218 297 +","match_part"]],"426","match"]],"urlTemplate":"lf-{Chunk}.json"}}