{"featureCount":2,"formatVersion":1,"histograms":{"meta":[{"arrayParams":{"chunkSize":10000,"length":1,"urlTemplate":"hist-20000-{Chunk}.json"},"basesPerBin":"20000"}],"stats":[{"basesPerBin":"20000","max":2,"mean":2}]},"intervals":{"classes":[{"attributes":["Start","End","Strand","Id","Name","Seq_id","Source","Subfeatures","Target_length","Type"],"isArrayAttr":{"Subfeatures":1}},{"attributes":["Start","End","Strand","Gap","Id","Seq_id","Source","Target","Type"],"isArrayAttr":{}},{"attributes":["Start","End","Strand","Id","Seq_id","Source","Target","Type"],"isArrayAttr":{}},{"attributes":["Start","End","Chunk"],"isArrayAttr":{"Sublist":1}}],"count":2,"lazyClass":3,"maxEnd":14900,"minStart":2183,"nclist":[[0,2183,7452,-1,"NODE_1390_length_14914_cov_5.843917:hit:100733:4.5.0.0","genemark-NODE_1390_length_14914_cov_5.843917-abinit-gene-0.1-mRNA-1","NODE_1390_length_14914_cov_5.843917","genemark",[[1,6094,7452,-1,"M1358","NODE_1390_length_14914_cov_5.843917:hsp:507721:4.5.0.0","NODE_1390_length_14914_cov_5.843917","genemark","genemark-NODE_1390_length_14914_cov_5.843917-abinit-gene-0.1-mRNA-1 3779 5136 +","match_part"],[1,5978,6024,-1,"M46","NODE_1390_length_14914_cov_5.843917:hsp:507722:4.5.0.0","NODE_1390_length_14914_cov_5.843917","genemark","genemark-NODE_1390_length_14914_cov_5.843917-abinit-gene-0.1-mRNA-1 3733 3778 +","match_part"],[1,2183,5915,-1,"M3732","NODE_1390_length_14914_cov_5.843917:hsp:507723:4.5.0.0","NODE_1390_length_14914_cov_5.843917","genemark","genemark-NODE_1390_length_14914_cov_5.843917-abinit-gene-0.1-mRNA-1 1 3732 +","match_part"]],"14914","match"],[0,14023,14900,1,"NODE_1390_length_14914_cov_5.843917:hit:100739:4.5.0.0","genemark-NODE_1390_length_14914_cov_5.843917-abinit-gene-0.0-mRNA-1","NODE_1390_length_14914_cov_5.843917","genemark",[[1,14023,14407,1,"M384","NODE_1390_length_14914_cov_5.843917:hsp:507737:4.5.0.0","NODE_1390_length_14914_cov_5.843917","genemark","genemark-NODE_1390_length_14914_cov_5.843917-abinit-gene-0.0-mRNA-1 1 384 +","match_part"],[1,14476,14505,1,"M29","NODE_1390_length_14914_cov_5.843917:hsp:507738:4.5.0.0","NODE_1390_length_14914_cov_5.843917","genemark","genemark-NODE_1390_length_14914_cov_5.843917-abinit-gene-0.0-mRNA-1 385 413 +","match_part"],[1,14588,14660,1,"M72","NODE_1390_length_14914_cov_5.843917:hsp:507739:4.5.0.0","NODE_1390_length_14914_cov_5.843917","genemark","genemark-NODE_1390_length_14914_cov_5.843917-abinit-gene-0.0-mRNA-1 414 485 +","match_part"],[1,14755,14900,1,"M145","NODE_1390_length_14914_cov_5.843917:hsp:507740:4.5.0.0","NODE_1390_length_14914_cov_5.843917","genemark","genemark-NODE_1390_length_14914_cov_5.843917-abinit-gene-0.0-mRNA-1 486 630 +","match_part"]],"14914","match"]],"urlTemplate":"lf-{Chunk}.json"}}