{"featureCount":1,"formatVersion":1,"histograms":{"meta":[{"arrayParams":{"chunkSize":10000,"length":1,"urlTemplate":"hist-5000-{Chunk}.json"},"basesPerBin":"5000"}],"stats":[{"basesPerBin":"5000","max":1,"mean":1}]},"intervals":{"classes":[{"attributes":["Start","End","Strand","Id","Name","Seq_id","Source","Subfeatures","Target_length","Type"],"isArrayAttr":{"Subfeatures":1}},{"attributes":["Start","End","Strand","Gap","Id","Seq_id","Source","Target","Type"],"isArrayAttr":{}},{"attributes":["Start","End","Strand","Id","Seq_id","Source","Target","Type"],"isArrayAttr":{}},{"attributes":["Start","End","Chunk"],"isArrayAttr":{"Sublist":1}}],"count":1,"lazyClass":3,"maxEnd":1169,"minStart":716,"nclist":[[0,716,1169,-1,"NODE_13395_length_1316_cov_1.386039:hit:3865:4.5.0.0","genemark-NODE_13395_length_1316_cov_1.386039-abinit-gene-0.1-mRNA-1","NODE_13395_length_1316_cov_1.386039","genemark",[[1,979,1169,-1,"M190","NODE_13395_length_1316_cov_1.386039:hsp:7766:4.5.0.0","NODE_13395_length_1316_cov_1.386039","genemark","genemark-NODE_13395_length_1316_cov_1.386039-abinit-gene-0.1-mRNA-1 111 300 +","match_part"],[1,851,915,-1,"M64","NODE_13395_length_1316_cov_1.386039:hsp:7767:4.5.0.0","NODE_13395_length_1316_cov_1.386039","genemark","genemark-NODE_13395_length_1316_cov_1.386039-abinit-gene-0.1-mRNA-1 47 110 +","match_part"],[1,716,762,-1,"M46","NODE_13395_length_1316_cov_1.386039:hsp:7768:4.5.0.0","NODE_13395_length_1316_cov_1.386039","genemark","genemark-NODE_13395_length_1316_cov_1.386039-abinit-gene-0.1-mRNA-1 1 46 +","match_part"]],"1316","match"]],"urlTemplate":"lf-{Chunk}.json"}}