{"featureCount":1,"formatVersion":1,"histograms":{"meta":[{"arrayParams":{"chunkSize":10000,"length":1,"urlTemplate":"hist-20000-{Chunk}.json"},"basesPerBin":"20000"}],"stats":[{"basesPerBin":"20000","max":1,"mean":1}]},"intervals":{"classes":[{"attributes":["Start","End","Strand","_aed","_eaed","_qi","Alias","Id","Name","Note","Seq_id","Source","Subfeatures","Type"],"isArrayAttr":{"Subfeatures":1}},{"attributes":["Start","End","Strand","Id","Seq_id","Source","Type"],"isArrayAttr":{}},{"attributes":["Start","End","Strand","Id","Phase","Seq_id","Source","Type"],"isArrayAttr":{}},{"attributes":["Start","End","Strand","_aed","_eaed","_merge_warning","_qi","Alias","Dbxref","Id","Name","Note","Seq_id","Source","Subfeatures","Type"],"isArrayAttr":{"Subfeatures":1}},{"attributes":["Start","End","Strand","_aed","_eaed","_qi","Alias","Dbxref","Id","Name","Note","Ontology_term","Seq_id","Source","Subfeatures","Type"],"isArrayAttr":{"Dbxref":1,"Ontology_term":1,"Subfeatures":1}},{"attributes":["Start","End","Strand","_aed","_eaed","_merge_warning","_qi","Alias","Dbxref","Id","Name","Note","Ontology_term","Seq_id","Source","Subfeatures","Type"],"isArrayAttr":{"Dbxref":1,"Ontology_term":1,"Subfeatures":1}},{"attributes":["Start","End","Strand","_aed","_eaed","_merge_warning","_qi","Alias","Id","Name","Note","Seq_id","Source","Subfeatures","Type"],"isArrayAttr":{"Subfeatures":1}},{"attributes":["Start","End","Strand","_aed","_eaed","_qi","Alias","Dbxref","Id","Name","Note","Seq_id","Source","Subfeatures","Type"],"isArrayAttr":{"Dbxref":1,"Subfeatures":1}},{"attributes":["Start","End","Chunk"],"isArrayAttr":{"Sublist":1}}],"count":1,"lazyClass":8,"maxEnd":4137,"minStart":2360,"nclist":[[7,2360,4137,-1,"0.07","0.07","113|1|0.75|1|1|1|4|0|480","maker-NODE_4984_length_5114_cov_3.682966-augustus-gene-0.3-mRNA-1",["InterPro:IPR027806","Pfam:PF13359"],"TAER_00008101-RA","TAER_00008101-RA","Similar to HARBI1: Putative nuclease HARBI1 (Homo sapiens OX=9606)","NODE_4984_length_5114_cov_3.682966","maker",[[1,2360,2840,-1,"TAER_00008101-RA:4","NODE_4984_length_5114_cov_3.682966","maker","exon"],[1,2903,3235,-1,"TAER_00008101-RA:3","NODE_4984_length_5114_cov_3.682966","maker","exon"],[1,3321,3508,-1,"TAER_00008101-RA:2","NODE_4984_length_5114_cov_3.682966","maker","exon"],[1,3580,4137,-1,"TAER_00008101-RA:1","NODE_4984_length_5114_cov_3.682966","maker","exon"],[1,4024,4137,-1,"TAER_00008101-RA:five_prime_utr","NODE_4984_length_5114_cov_3.682966","maker","five_prime_UTR"],[2,3580,4024,-1,"TAER_00008101-RA:cds",0,"NODE_4984_length_5114_cov_3.682966","maker","CDS"],[2,3321,3508,-1,"TAER_00008101-RA:cds",0,"NODE_4984_length_5114_cov_3.682966","maker","CDS"],[2,2903,3235,-1,"TAER_00008101-RA:cds",2,"NODE_4984_length_5114_cov_3.682966","maker","CDS"],[2,2360,2840,-1,"TAER_00008101-RA:cds",0,"NODE_4984_length_5114_cov_3.682966","maker","CDS"]],"mRNA"]],"urlTemplate":"lf-{Chunk}.json"}}