{"featureCount":1,"formatVersion":1,"histograms":{"meta":[{"arrayParams":{"chunkSize":10000,"length":1,"urlTemplate":"hist-5000-{Chunk}.json"},"basesPerBin":"5000"}],"stats":[{"basesPerBin":"5000","max":1,"mean":1}]},"intervals":{"classes":[{"attributes":["Start","End","Strand","Id","Name","Score","Seq_id","Source","Subfeatures","Target_length","Type"],"isArrayAttr":{"Subfeatures":1}},{"attributes":["Start","End","Strand","Gap","Id","Score","Seq_id","Source","Target","Type"],"isArrayAttr":{}},{"attributes":["Start","End","Chunk"],"isArrayAttr":{"Sublist":1}}],"count":1,"lazyClass":2,"maxEnd":1016,"minStart":85,"nclist":[[0,85,1016,-1,"NODE_13768_length_1272_cov_4.109170:hit:4898:4.5.0.0","augustus-NODE_13768_length_1272_cov_4.109170-abinit-gene-0.0-mRNA-1",0.4,"NODE_13768_length_1272_cov_4.109170","augustus",[[1,959,1016,-1,"M57","NODE_13768_length_1272_cov_4.109170:hsp:9842:4.5.0.0",0.4,"NODE_13768_length_1272_cov_4.109170","augustus","augustus-NODE_13768_length_1272_cov_4.109170-abinit-gene-0.0-mRNA-1 346 402 +","match_part"],[1,740,880,-1,"M140","NODE_13768_length_1272_cov_4.109170:hsp:9843:4.5.0.0",0.4,"NODE_13768_length_1272_cov_4.109170","augustus","augustus-NODE_13768_length_1272_cov_4.109170-abinit-gene-0.0-mRNA-1 206 345 +","match_part"],[1,470,604,-1,"M134","NODE_13768_length_1272_cov_4.109170:hsp:9844:4.5.0.0",0.4,"NODE_13768_length_1272_cov_4.109170","augustus","augustus-NODE_13768_length_1272_cov_4.109170-abinit-gene-0.0-mRNA-1 72 205 +","match_part"],[1,356,366,-1,"M10","NODE_13768_length_1272_cov_4.109170:hsp:9845:4.5.0.0",0.4,"NODE_13768_length_1272_cov_4.109170","augustus","augustus-NODE_13768_length_1272_cov_4.109170-abinit-gene-0.0-mRNA-1 62 71 +","match_part"],[1,230,267,-1,"M37","NODE_13768_length_1272_cov_4.109170:hsp:9846:4.5.0.0",0.4,"NODE_13768_length_1272_cov_4.109170","augustus","augustus-NODE_13768_length_1272_cov_4.109170-abinit-gene-0.0-mRNA-1 25 61 +","match_part"],[1,85,109,-1,"M24","NODE_13768_length_1272_cov_4.109170:hsp:9847:4.5.0.0",0.4,"NODE_13768_length_1272_cov_4.109170","augustus","augustus-NODE_13768_length_1272_cov_4.109170-abinit-gene-0.0-mRNA-1 1 24 +","match_part"]],"1272","match"]],"urlTemplate":"lf-{Chunk}.json"}}