{"featureCount":1,"formatVersion":1,"histograms":{"meta":[{"arrayParams":{"chunkSize":10000,"length":1,"urlTemplate":"hist-10000-{Chunk}.json"},"basesPerBin":"10000"}],"stats":[{"basesPerBin":"10000","max":1,"mean":1}]},"intervals":{"classes":[{"attributes":["Start","End","Strand","Id","Name","Seq_id","Source","Subfeatures","Target_length","Type"],"isArrayAttr":{"Subfeatures":1}},{"attributes":["Start","End","Strand","Gap","Id","Seq_id","Source","Target","Type"],"isArrayAttr":{}},{"attributes":["Start","End","Strand","Id","Seq_id","Source","Target","Type"],"isArrayAttr":{}},{"attributes":["Start","End","Chunk"],"isArrayAttr":{"Sublist":1}}],"count":1,"lazyClass":3,"maxEnd":3140,"minStart":1184,"nclist":[[0,1184,3140,1,"NODE_7044_length_3187_cov_0.869935:hit:8462:4.5.0.0","genemark-NODE_7044_length_3187_cov_0.869935-abinit-gene-0.2-mRNA-1","NODE_7044_length_3187_cov_0.869935","genemark",[[1,1184,1572,1,"M388","NODE_7044_length_3187_cov_0.869935:hsp:25726:4.5.0.0","NODE_7044_length_3187_cov_0.869935","genemark","genemark-NODE_7044_length_3187_cov_0.869935-abinit-gene-0.2-mRNA-1 1 388 +","match_part"],[1,1636,2234,1,"M598","NODE_7044_length_3187_cov_0.869935:hsp:25727:4.5.0.0","NODE_7044_length_3187_cov_0.869935","genemark","genemark-NODE_7044_length_3187_cov_0.869935-abinit-gene-0.2-mRNA-1 389 986 +","match_part"],[1,2320,2403,1,"M83","NODE_7044_length_3187_cov_0.869935:hsp:25728:4.5.0.0","NODE_7044_length_3187_cov_0.869935","genemark","genemark-NODE_7044_length_3187_cov_0.869935-abinit-gene-0.2-mRNA-1 987 1069 +","match_part"],[1,2462,2839,1,"M377","NODE_7044_length_3187_cov_0.869935:hsp:25729:4.5.0.0","NODE_7044_length_3187_cov_0.869935","genemark","genemark-NODE_7044_length_3187_cov_0.869935-abinit-gene-0.2-mRNA-1 1070 1446 +","match_part"],[1,2921,3140,1,"M219","NODE_7044_length_3187_cov_0.869935:hsp:25730:4.5.0.0","NODE_7044_length_3187_cov_0.869935","genemark","genemark-NODE_7044_length_3187_cov_0.869935-abinit-gene-0.2-mRNA-1 1447 1665 +","match_part"]],"3187","match"]],"urlTemplate":"lf-{Chunk}.json"}}