{"featureCount":1,"formatVersion":1,"histograms":{"meta":[{"arrayParams":{"chunkSize":10000,"length":1,"urlTemplate":"hist-10000-{Chunk}.json"},"basesPerBin":"10000"}],"stats":[{"basesPerBin":"10000","max":1,"mean":1}]},"intervals":{"classes":[{"attributes":["Start","End","Strand","Id","Name","Seq_id","Source","Subfeatures","Target_length","Type"],"isArrayAttr":{"Subfeatures":1}},{"attributes":["Start","End","Strand","Gap","Id","Seq_id","Source","Target","Type"],"isArrayAttr":{}},{"attributes":["Start","End","Strand","Id","Seq_id","Source","Target","Type"],"isArrayAttr":{}},{"attributes":["Start","End","Chunk"],"isArrayAttr":{"Sublist":1}}],"count":1,"lazyClass":3,"maxEnd":2913,"minStart":64,"nclist":[[0,64,2913,-1,"NODE_7416_length_2932_cov_6.681640:hit:10993:4.5.0.0","genemark-NODE_7416_length_2932_cov_6.681640-abinit-gene-0.1-mRNA-1","NODE_7416_length_2932_cov_6.681640","genemark",[[1,2567,2913,-1,"M346","NODE_7416_length_2932_cov_6.681640:hsp:32549:4.5.0.0","NODE_7416_length_2932_cov_6.681640","genemark","genemark-NODE_7416_length_2932_cov_6.681640-abinit-gene-0.1-mRNA-1 2277 2622 +","match_part"],[1,2404,2489,-1,"M85","NODE_7416_length_2932_cov_6.681640:hsp:32550:4.5.0.0","NODE_7416_length_2932_cov_6.681640","genemark","genemark-NODE_7416_length_2932_cov_6.681640-abinit-gene-0.1-mRNA-1 2192 2276 +","match_part"],[1,1856,2345,-1,"M489","NODE_7416_length_2932_cov_6.681640:hsp:32551:4.5.0.0","NODE_7416_length_2932_cov_6.681640","genemark","genemark-NODE_7416_length_2932_cov_6.681640-abinit-gene-0.1-mRNA-1 1703 2191 +","match_part"],[1,64,1766,-1,"M1702","NODE_7416_length_2932_cov_6.681640:hsp:32552:4.5.0.0","NODE_7416_length_2932_cov_6.681640","genemark","genemark-NODE_7416_length_2932_cov_6.681640-abinit-gene-0.1-mRNA-1 1 1702 +","match_part"]],"2932","match"]],"urlTemplate":"lf-{Chunk}.json"}}