{"featureCount":2,"formatVersion":1,"histograms":{"meta":[{"arrayParams":{"chunkSize":10000,"length":1,"urlTemplate":"hist-20000-{Chunk}.json"},"basesPerBin":"20000"}],"stats":[{"basesPerBin":"20000","max":2,"mean":2}]},"intervals":{"classes":[{"attributes":["Start","End","Strand","Id","Name","Seq_id","Source","Subfeatures","Target_length","Type"],"isArrayAttr":{"Subfeatures":1}},{"attributes":["Start","End","Strand","Gap","Id","Seq_id","Source","Target","Type"],"isArrayAttr":{}},{"attributes":["Start","End","Strand","Id","Seq_id","Source","Target","Type"],"isArrayAttr":{}},{"attributes":["Start","End","Chunk"],"isArrayAttr":{"Sublist":1}}],"count":2,"lazyClass":3,"maxEnd":8756,"minStart":188,"nclist":[[0,188,3997,-1,"NODE_2732_length_8782_cov_7.343306:hit:19192:4.5.0.0","genemark-NODE_2732_length_8782_cov_7.343306-abinit-gene-0.3-mRNA-1","NODE_2732_length_8782_cov_7.343306","genemark",[[1,3786,3997,-1,"M211","NODE_2732_length_8782_cov_7.343306:hsp:82661:4.5.0.0","NODE_2732_length_8782_cov_7.343306","genemark","genemark-NODE_2732_length_8782_cov_7.343306-abinit-gene-0.3-mRNA-1 3513 3723 +","match_part"],[1,188,3700,-1,"M3512","NODE_2732_length_8782_cov_7.343306:hsp:82662:4.5.0.0","NODE_2732_length_8782_cov_7.343306","genemark","genemark-NODE_2732_length_8782_cov_7.343306-abinit-gene-0.3-mRNA-1 1 3512 +","match_part"]],"8782","match"],[0,8586,8756,-1,"NODE_2732_length_8782_cov_7.343306:hit:19194:4.5.0.0","genemark-NODE_2732_length_8782_cov_7.343306-abinit-gene-0.4-mRNA-1","NODE_2732_length_8782_cov_7.343306","genemark",[[1,8701,8756,-1,"M55","NODE_2732_length_8782_cov_7.343306:hsp:82668:4.5.0.0","NODE_2732_length_8782_cov_7.343306","genemark","genemark-NODE_2732_length_8782_cov_7.343306-abinit-gene-0.4-mRNA-1 27 81 +","match_part"],[1,8586,8612,-1,"M26","NODE_2732_length_8782_cov_7.343306:hsp:82669:4.5.0.0","NODE_2732_length_8782_cov_7.343306","genemark","genemark-NODE_2732_length_8782_cov_7.343306-abinit-gene-0.4-mRNA-1 1 26 +","match_part"]],"8782","match"]],"urlTemplate":"lf-{Chunk}.json"}}