{"featureCount":2,"formatVersion":1,"histograms":{"meta":[{"arrayParams":{"chunkSize":10000,"length":1,"urlTemplate":"hist-10000-{Chunk}.json"},"basesPerBin":"10000"}],"stats":[{"basesPerBin":"10000","max":2,"mean":2}]},"intervals":{"classes":[{"attributes":["Start","End","Strand","_aed","_eaed","_qi","Id","Name","Seq_id","Source","Subfeatures","Type"],"isArrayAttr":{"Subfeatures":1}},{"attributes":["Start","End","Strand","Id","Seq_id","Source","Type"],"isArrayAttr":{}},{"attributes":["Start","End","Strand","Id","Phase","Seq_id","Source","Type"],"isArrayAttr":{}},{"attributes":["Start","End","Strand","_aed","_eaed","_merge_warning","_qi","Id","Name","Seq_id","Source","Subfeatures","Type"],"isArrayAttr":{"Subfeatures":1}},{"attributes":["Start","End","Chunk"],"isArrayAttr":{"Sublist":1}}],"count":2,"lazyClass":4,"maxEnd":5412,"minStart":4011,"nclist":[[0,4011,4694,1,"0.13","0.13","90|0.66|0.75|1|0.33|0.25|4|0|154","maker-NODE_4711_length_5452_cov_9.267793-snap-gene-0.14-mRNA-1","maker-NODE_4711_length_5452_cov_9.267793-snap-gene-0.14-mRNA-1","NODE_4711_length_5452_cov_9.267793","maker",[[1,4011,4218,1,"maker-NODE_4711_length_5452_cov_9.267793-snap-gene-0.14-mRNA-1:1","NODE_4711_length_5452_cov_9.267793","maker","exon"],[1,4329,4611,1,"maker-NODE_4711_length_5452_cov_9.267793-snap-gene-0.14-mRNA-1:2","NODE_4711_length_5452_cov_9.267793","maker","exon"],[1,4628,4694,1,"maker-NODE_4711_length_5452_cov_9.267793-snap-gene-0.14-mRNA-1:3","NODE_4711_length_5452_cov_9.267793","maker","exon"],[1,4011,4101,1,"maker-NODE_4711_length_5452_cov_9.267793-snap-gene-0.14-mRNA-1:five_prime_utr","NODE_4711_length_5452_cov_9.267793","maker","five_prime_UTR"],[2,4101,4218,1,"maker-NODE_4711_length_5452_cov_9.267793-snap-gene-0.14-mRNA-1:cds",0,"NODE_4711_length_5452_cov_9.267793","maker","CDS"],[2,4329,4611,1,"maker-NODE_4711_length_5452_cov_9.267793-snap-gene-0.14-mRNA-1:cds",0,"NODE_4711_length_5452_cov_9.267793","maker","CDS"],[2,4628,4694,1,"maker-NODE_4711_length_5452_cov_9.267793-snap-gene-0.14-mRNA-1:cds",0,"NODE_4711_length_5452_cov_9.267793","maker","CDS"]],"mRNA"],[0,4784,5412,1,"0.04","0.04","0|0.66|0.5|0.75|1|0.5|4|0|148","maker-NODE_4711_length_5452_cov_9.267793-snap-gene-0.15-mRNA-1","maker-NODE_4711_length_5452_cov_9.267793-snap-gene-0.15-mRNA-1","NODE_4711_length_5452_cov_9.267793","maker",[[1,4784,4973,1,"maker-NODE_4711_length_5452_cov_9.267793-snap-gene-0.15-mRNA-1:1","NODE_4711_length_5452_cov_9.267793","maker","exon"],[1,5060,5235,1,"maker-NODE_4711_length_5452_cov_9.267793-snap-gene-0.15-mRNA-1:2","NODE_4711_length_5452_cov_9.267793","maker","exon"],[1,5329,5412,1,"maker-NODE_4711_length_5452_cov_9.267793-snap-gene-0.15-mRNA-1:3","NODE_4711_length_5452_cov_9.267793","maker","exon"],[2,4784,4973,1,"maker-NODE_4711_length_5452_cov_9.267793-snap-gene-0.15-mRNA-1:cds",0,"NODE_4711_length_5452_cov_9.267793","maker","CDS"],[2,5060,5235,1,"maker-NODE_4711_length_5452_cov_9.267793-snap-gene-0.15-mRNA-1:cds",0,"NODE_4711_length_5452_cov_9.267793","maker","CDS"],[2,5329,5412,1,"maker-NODE_4711_length_5452_cov_9.267793-snap-gene-0.15-mRNA-1:cds",2,"NODE_4711_length_5452_cov_9.267793","maker","CDS"]],"mRNA"]],"urlTemplate":"lf-{Chunk}.json"}}