{"featureCount":2,"formatVersion":1,"histograms":{"meta":[{"arrayParams":{"chunkSize":10000,"length":1,"urlTemplate":"hist-50000-{Chunk}.json"},"basesPerBin":"50000"}],"stats":[{"basesPerBin":"50000","max":2,"mean":2}]},"intervals":{"classes":[{"attributes":["Start","End","Strand","Id","Name","Score","Seq_id","Source","Subfeatures","Target_length","Type"],"isArrayAttr":{"Subfeatures":1}},{"attributes":["Start","End","Strand","Gap","Id","Score","Seq_id","Source","Target","Type"],"isArrayAttr":{}},{"attributes":["Start","End","Chunk"],"isArrayAttr":{"Sublist":1}}],"count":2,"lazyClass":2,"maxEnd":20366,"minStart":13708,"nclist":[[0,13708,14158,1,"NODE_170_length_37804_cov_8.130106:hit:21614:4.5.0.0","augustus-NODE_170_length_37804_cov_8.130106-abinit-gene-0.5-mRNA-1",0.82,"NODE_170_length_37804_cov_8.130106","augustus",[[1,13708,14158,1,"M450","NODE_170_length_37804_cov_8.130106:hsp:112058:4.5.0.0",0.82,"NODE_170_length_37804_cov_8.130106","augustus","augustus-NODE_170_length_37804_cov_8.130106-abinit-gene-0.5-mRNA-1 1 450 +","match_part"]],"37804","match"],[0,19471,20366,1,"NODE_170_length_37804_cov_8.130106:hit:21617:4.5.0.0","augustus-NODE_170_length_37804_cov_8.130106-abinit-gene-0.6-mRNA-1",0.5,"NODE_170_length_37804_cov_8.130106","augustus",[[1,19471,19541,1,"M70","NODE_170_length_37804_cov_8.130106:hsp:112063:4.5.0.0",0.5,"NODE_170_length_37804_cov_8.130106","augustus","augustus-NODE_170_length_37804_cov_8.130106-abinit-gene-0.6-mRNA-1 1 70 +","match_part"],[1,19623,20125,1,"M502","NODE_170_length_37804_cov_8.130106:hsp:112064:4.5.0.0",0.5,"NODE_170_length_37804_cov_8.130106","augustus","augustus-NODE_170_length_37804_cov_8.130106-abinit-gene-0.6-mRNA-1 71 572 +","match_part"],[1,20227,20366,1,"M139","NODE_170_length_37804_cov_8.130106:hsp:112065:4.5.0.0",0.5,"NODE_170_length_37804_cov_8.130106","augustus","augustus-NODE_170_length_37804_cov_8.130106-abinit-gene-0.6-mRNA-1 573 711 +","match_part"]],"37804","match"]],"urlTemplate":"lf-{Chunk}.json"}}